[{"__symbolic":"module","version":3,"metadata":{"OptionBuilder":{"__symbolic":"class","decorators":[{"__symbolic":"call","expression":{"__symbolic":"reference","module":"@angular/core","name":"Injectable"}}],"members":{"googlizeAllInputs":[{"__symbolic":"method"}],"googlizeMultiple":[{"__symbolic":"method"}],"googlize":[{"__symbolic":"method"}],"getLatLng":[{"__symbolic":"method"}],"getJSONParsed":[{"__symbolic":"method"}],"getAnyMapObject":[{"__symbolic":"method"}],"getAnyMapConstant":[{"__symbolic":"method"}],"getMapControlOption":[{"__symbolic":"method"}],"getDateObject":[{"__symbolic":"method"}],"getMapIcons":[{"__symbolic":"method"}],"getMarkerIcon":[{"__symbolic":"method"}],"onlyOptionsGiven":[{"__symbolic":"method"}]}}}},{"__symbolic":"module","version":1,"metadata":{"OptionBuilder":{"__symbolic":"class","decorators":[{"__symbolic":"call","expression":{"__symbolic":"reference","module":"@angular/core","name":"Injectable"}}],"members":{"googlizeAllInputs":[{"__symbolic":"method"}],"googlizeMultiple":[{"__symbolic":"method"}],"googlize":[{"__symbolic":"method"}],"getLatLng":[{"__symbolic":"method"}],"getJSONParsed":[{"__symbolic":"method"}],"getAnyMapObject":[{"__symbolic":"method"}],"getAnyMapConstant":[{"__symbolic":"method"}],"getMapControlOption":[{"__symbolic":"method"}],"getDateObject":[{"__symbolic":"method"}],"getMapIcons":[{"__symbolic":"method"}],"getMarkerIcon":[{"__symbolic":"method"}],"onlyOptionsGiven":[{"__symbolic":"method"}]}}}}]